plover_ninja/__init__.py
plover_ninja/plover_hook.py
plover_ninja/storage.py
plover_ninja/lessons/__init__.py
plover_ninja/lessons/make_a_new_friend.py
plover_ninja/lessons/need_for_speed.py
plover_ninja/lessons/remember_me.py
plover_ninja/plugins/__init__.py
plover_ninja/plugins/ninja_plugin.py
plover_ninja/plugins/ninja_repl.py
plover_ninja/plugins/ninja_test.py
plover_ninja/plugins/stroke_efficiency_log.py
plover_ninja/wikipedia_word_frequency/__init__.py
plover_ninja/wikipedia_word_frequency/enwiki-20210820-words-frequency.txt
plover_ninja/wikipedia_word_frequency/word_frequency_list_manager.py
plover_ninja-0.0.13.dist-info/LICENSE
plover_ninja-0.0.13.dist-info/METADATA
plover_ninja-0.0.13.dist-info/WHEEL
plover_ninja-0.0.13.dist-info/entry_points.txt
plover_ninja-0.0.13.dist-info/top_level.txt
plover_ninja-0.0.13.dist-info/zip-safe
plover_ninja-0.0.13.dist-info/RECORD
