Metadata-Version: 2.1
Name: plover-ninja
Version: 0.0.13
Summary: A Plover plugin that uses stroke data to make practice suggestions and show writing statistics
Home-page: https://github.com/jladdjr/plover-ninja
Author: Jim Ladd
Author-email: jladdjr@gmail.com
License: UNKNOWN
Project-URL: Changelog, https://github.com/jladdjr/plover-ninja/blob/main/NEWS.md
Project-URL: Bug Tracker, https://github.com/jladdjr/plover-ninja/issues
Project-URL: Source Code, https://github.com/jladdjr/plover-ninja
Keywords: plover plover_plugin
Platform: UNKNOWN
Classifier: Programming Language :: Python :: 3
Classifier: License :: OSI Approved :: GNU General Public License v2 or later (GPLv2+)
Classifier: Development Status :: 3 - Alpha
Classifier: Operating System :: POSIX :: BSD
Classifier: Operating System :: POSIX :: Linux
Classifier: Operating System :: MacOS :: MacOS X
Classifier: Operating System :: Microsoft :: Windows
Requires-Dist: plover (>=4.0.0.dev8)
